modelslab/__init__.py
modelslab/ai_chat_llm.py
modelslab/ai_video.py
modelslab/ai_voice_and_audio.py
modelslab/api.py
modelslab/community_models.py
modelslab/controlnet.py
modelslab/deepfake.py
modelslab/ep_general.py
modelslab/ep_image_edit.py
modelslab/ep_realtime.py
modelslab/ep_txt2img.py
modelslab/ep_video.py
modelslab/ep_voice_cloning.py
modelslab/helper.py
modelslab/image_editing.py
modelslab/miscs.py
modelslab/realtime.py
modelslab/text_to_3d.py
modelslab/train_model.py
modelslab-0.2.dist-info/LICENSE
modelslab-0.2.dist-info/METADATA
modelslab-0.2.dist-info/WHEEL
modelslab-0.2.dist-info/top_level.txt
modelslab-0.2.dist-info/RECORD
